subwiz/__init__.py
subwiz/cli.py
subwiz/cli_printer.py
subwiz/main.py
subwiz/model.py
subwiz/resolve.py
subwiz/type.py
subwiz-1.0.1.dist-info/licenses/LICENSE
subwiz-1.0.1.dist-info/METADATA
subwiz-1.0.1.dist-info/WHEEL
subwiz-1.0.1.dist-info/entry_points.txt
subwiz-1.0.1.dist-info/top_level.txt
subwiz-1.0.1.dist-info/RECORD
