Metadata-Version: 2.4
Name: subwiz
Version: 1.0.1
Summary: A lightweight GPT model, trained to discover subdomains.
Author-email: Klaas Meinke <klaas@hadrian.io>
License: MIT License
Project-URL: Source, https://github.com/hadriansecurity/subwiz
Keywords: machine learning,recon,subdomains,transformers
Requires-Python: <3.14,>=3.9
License-File: LICENSE
Requires-Dist: aiodns>=1.0.0
Requires-Dist: huggingface-hub>=0.5.0
Requires-Dist: pydantic>=1.10.0
Requires-Dist: tldextract>=3.0.0
Requires-Dist: torch>=2.3.0
Requires-Dist: transformers>=4.34.0
Dynamic: license-file
